README.rst
setup.py
djenius.egg-info/PKG-INFO
djenius.egg-info/SOURCES.txt
djenius.egg-info/dependency_links.txt
djenius.egg-info/requires.txt
djenius.egg-info/top_level.txt
djenius/bin/__init__.py
djenius/bin/backend.py
djenius/bin/resolver.py
djenius/fts/__init__.py
djenius/mpv/__init__.py
djenius/resolver/__init__.py
djenius/resolver/googletts.py
djenius/resolver/spotify.py
djenius/resolver/youtube.py
djenius/server/__init__.py
djenius/server/main.py
djenius/server/settings.py
djenius/server/song.py
frontend/build/asset-manifest.json
frontend/build/index.html
frontend/build/manifest.json
frontend/build/no-cover.jpg
frontend/build/service-worker.js
frontend/build/static/css/main.f256f719.chunk.css
frontend/build/static/js/1.fab1bc6d.chunk.js
frontend/build/static/js/1.fab1bc6d.chunk.js.map
frontend/build/static/js/main.2f6ff3ff.chunk.js
frontend/build/static/js/main.2f6ff3ff.chunk.js.map