Metadata-Version: 1.1
Name: djenius
Version: 1.0
Summary: A collaborative jukebox for no-Internet environments.
Home-page: https://github.com/prologin/djenius/
Author: Alexandre Macabies
Author-email: UNKNOWN
License: UNKNOWN
Platform: UNKNOWN
Classifier: License :: OSI Approved :: GNU General Public License v3 (GPLv3)
